[{"run_id": 15022380472, "name": "\u508d\u665a\u8dd1\u6b65", "distance": 2902.6, "moving_time": "0:21:52", "type": "Run", "subtype": "Run", "start_date": "2017-03-27 12:39:06+00:00", "start_date_local": "2017-03-27 20:39:06", "location_country": null, "summary_polyline": "", "average_heartrate": null, "average_speed": 2.212, "elevation_gain": 19.7, "streak": 1}, {"run_id": 15022379889, "name": "\u508d\u665a\u8dd1\u6b65", "distance": 3338.2, "moving_time": "0:24:57", "type": "Run", "subtype": "Run", "start_date": "2017-03-29 12:16:14+00:00", "start_date_local": "2017-03-29 20:16:14", "location_country": null, "summary_polyline": "", "average_heartrate": null, "average_speed": 2.23, "elevation_gain": 47.5, "streak": 1}, {"run_id": 15041247786, "name": "\u508d\u665a\u8dd1\u6b65", "distance": 3338.2, "moving_time": "0:24:57", "type": "Run", "subtype": "Run", "start_date": "2017-03-29 12:16:14+00:00", "start_date_local": "2017-03-29 20:16:14", "location_country": null, "summary_polyline": "", "average_heartrate": null, "average_speed": 2.23, "elevation_gain": 47.5, "streak": 1}, {"run_id": 15041454442, "name": "\u508d\u665a\u8dd1\u6b65", "distance": 3338.2, "moving_time": "0:24:57", "type": "Run", "subtype": "Run", "start_date": "2017-03-29 12:16:14+00:00", "start_date_local": "2017-03-29 20:16:14", "location_country": null, "summary_polyline": "", "average_heartrate": null, "average_speed": 2.23, "elevation_gain": 47.5, "streak": 1}, {"run_id": 15041717463, "name": "\u508d\u665a\u8dd1\u6b65", "distance": 3338.2, "moving_time": "0:24:57", "type": "Run", "subtype": "Run", "start_date": "2017-03-29 12:16:14+00:00", "start_date_local": "2017-03-29 20:16:14", "location_country": null, "summary_polyline": "", "average_heartrate": null, "average_speed": 2.23, "elevation_gain": 47.5, "streak": 1}, {"run_id": 15045702521, "name": "\u508d\u665a\u8dd1\u6b65", "distance": 3338.2, "moving_time": "0:24:57", "type": "Run", "subtype": "Run", "start_date": "2017-03-29 12:16:14+00:00", "start_date_local": "2017-03-29 20:16:14", "location_country": null, "summary_polyline": "", "average_heartrate": null, "average_speed": 2.23, "elevation_gain": 47.5, "streak": 1}, {"run_id": 15052054044, "name": "\u508d\u665a\u8dd1\u6b65", "distance": 3338.2, "moving_time": "0:24:57", "type": "Run", "subtype": "Run", "start_date": "2017-03-29 12:16:14+00:00", "start_date_local": "2017-03-29 20:16:14", "location_country": null, "summary_polyline": "", "average_heartrate": null, "average_speed": 2.23, "elevation_gain": 47.5, "streak": 1}, {"run_id": 15057204574, "name": "\u508d\u665a\u8dd1\u6b65", "distance": 3338.2, "moving_time": "0:24:57", "type": "Run", "subtype": "Run", "start_date": "2017-03-29 12:16:14+00:00", "start_date_local": "2017-03-29 20:16:14", "location_country": null, "summary_polyline": "", "average_heartrate": null, "average_speed": 2.23, "elevation_gain": 47.5, "streak": 1}, {"run_id": 15063521351, "name": "\u508d\u665a\u8dd1\u6b65", "distance": 3338.2, "moving_time": "0:24:57", "type": "Run", "subtype": "Run", "start_date": "2017-03-29 12:16:14+00:00", "start_date_local": "2017-03-29 20:16:14", "location_country": null, "summary_polyline": "", "average_heartrate": null, "average_speed": 2.23, "elevation_gain": 47.0, "streak": 1}, {"run_id": 15068585656, "name": "\u508d\u665a\u8dd1\u6b65", "distance": 3338.2, "moving_time": "0:24:57", "type": "Run", "subtype": "Run", "start_date": "2017-03-29 12:16:14+00:00", "start_date_local": "2017-03-29 20:16:14", "location_country": null, "summary_polyline": "", "average_heartrate": null, "average_speed": 2.23, "elevation_gain": 47.0, "streak": 1}, {"run_id": 15074239658, "name": "\u508d\u665a\u8dd1\u6b65", "distance": 3338.2, "moving_time": "0:24:57", "type": "Run", "subtype": "Run", "start_date": "2017-03-29 12:16:14+00:00", "start_date_local": "2017-03-29 20:16:14", "location_country": null, "summary_polyline": "", "average_heartrate": null, "average_speed": 2.23, "elevation_gain": 47.0, "streak": 1}, {"run_id": 15084040442, "name": "\u508d\u665a\u8dd1\u6b65", "distance": 3338.2, "moving_time": "0:24:57", "type": "Run", "subtype": "Run", "start_date": "2017-03-29 12:16:14+00:00", "start_date_local": "2017-03-29 20:16:14", "location_country": null, "summary_polyline": "", "average_heartrate": null, "average_speed": 2.23, "elevation_gain": 47.0, "streak": 1}, {"run_id": 15091723885, "name": "\u508d\u665a\u8dd1\u6b65", "distance": 3338.2, "moving_time": "0:24:57", "type": "Run", "subtype": "Run", "start_date": "2017-03-29 12:16:14+00:00", "start_date_local": "2017-03-29 20:16:14", "location_country": null, "summary_polyline": "", "average_heartrate": null, "average_speed": 2.23, "elevation_gain": 47.0, "streak": 1}, {"run_id": 15022379408, "name": "\u508d\u665a\u8dd1\u6b65", "distance": 2550.5, "moving_time": "0:19:20", "type": "Run", "subtype": "Run", "start_date": "2017-04-01 12:56:33+00:00", "start_date_local": "2017-04-01 20:56:33", "location_country": null, "summary_polyline": "", "average_heartrate": null, "average_speed": 2.199, "elevation_gain": 37.3, "streak": 1}, {"run_id": 15022379224, "name": "\u508d\u665a\u8dd1\u6b65", "distance": 686.9, "moving_time": "0:05:35", "type": "Run", "subtype": "Run", "start_date": "2017-05-31 12:42:08+00:00", "start_date_local": "2017-05-31 20:42:08", "location_country": null, "summary_polyline": "", "average_heartrate": null, "average_speed": 2.051, "elevation_gain": 7.9, "streak": 1}, {"run_id": 15041247531, "name": "\u508d\u665a\u8dd1\u6b65", "distance": 686.9, "moving_time": "0:05:35", "type": "Run", "subtype": "Run", "start_date": "2017-05-31 12:42:08+00:00", "start_date_local": "2017-05-31 20:42:08", "location_country": null, "summary_polyline": "", "average_heartrate": null, "average_speed": 2.051, "elevation_gain": 7.9, "streak": 1}, {"run_id": 15041454308, "name": "\u508d\u665a\u8dd1\u6b65", "distance": 686.9, "moving_time": "0:05:35", "type": "Run", "subtype": "Run", "start_date": "2017-05-31 12:42:08+00:00", "start_date_local": "2017-05-31 20:42:08", "location_country": null, "summary_polyline": "", "average_heartrate": null, "average_speed": 2.051, "elevation_gain": 7.9, "streak": 1}, {"run_id": 15041717224, "name": "\u508d\u665a\u8dd1\u6b65", "distance": 686.9, "moving_time": "0:05:35", "type": "Run", "subtype": "Run", "start_date": "2017-05-31 12:42:08+00:00", "start_date_local": "2017-05-31 20:42:08", "location_country": null, "summary_polyline": "", "average_heartrate": null, "average_speed": 2.051, "elevation_gain": 7.9, "streak": 1}, {"run_id": 15045702106, "name": "\u508d\u665a\u8dd1\u6b65", "distance": 686.9, "moving_time": "0:05:35", "type": "Run", "subtype": "Run", "start_date": "2017-05-31 12:42:08+00:00", "start_date_local": "2017-05-31 20:42:08", "location_country": null, "summary_polyline": "", "average_heartrate": null, "average_speed": 2.051, "elevation_gain": 7.9, "streak": 1}, {"run_id": 15052053554, "name": "\u508d\u665a\u8dd1\u6b65", "distance": 686.9, "moving_time": "0:05:35", "type": "Run", "subtype": "Run", "start_date": "2017-05-31 12:42:08+00:00", "start_date_local": "2017-05-31 20:42:08", "location_country": null, "summary_polyline": "", "average_heartrate": null, "average_speed": 2.051, "elevation_gain": 7.9, "streak": 1}, {"run_id": 15057204244, "name": "\u508d\u665a\u8dd1\u6b65", "distance": 686.9, "moving_time": "0:05:35", "type": "Run", "subtype": "Run", "start_date": "2017-05-31 12:42:08+00:00", "start_date_local": "2017-05-31 20:42:08", "location_country": null, "summary_polyline": "", "average_heartrate": null, "average_speed": 2.051, "elevation_gain": 7.9, "streak": 1}, {"run_id": 15063521148, "name": "\u508d\u665a\u8dd1\u6b65", "distance": 686.9, "moving_time": "0:05:35", "type": "Run", "subtype": "Run", "start_date": "2017-05-31 12:42:08+00:00", "start_date_local": "2017-05-31 20:42:08", "location_country": null, "summary_polyline": "", "average_heartrate": null, "average_speed": 2.051, "elevation_gain": 7.8, "streak": 1}, {"run_id": 15068585443, "name": "\u508d\u665a\u8dd1\u6b65", "distance": 686.9, "moving_time": "0:05:35", "type": "Run", "subtype": "Run", "start_date": "2017-05-31 12:42:08+00:00", "start_date_local": "2017-05-31 20:42:08", "location_country": null, "summary_polyline": "", "average_heartrate": null, "average_speed": 2.051, "elevation_gain": 7.8, "streak": 1}, {"run_id": 15074239489, "name": "\u508d\u665a\u8dd1\u6b65", "distance": 686.9, "moving_time": "0:05:35", "type": "Run", "subtype": "Run", "start_date": "2017-05-31 12:42:08+00:00", "start_date_local": "2017-05-31 20:42:08", "location_country": null, "summary_polyline": "", "average_heartrate": null, "average_speed": 2.051, "elevation_gain": 7.8, "streak": 1}, {"run_id": 15084040063, "name": "\u508d\u665a\u8dd1\u6b65", "distance": 686.9, "moving_time": "0:05:35", "type": "Run", "subtype": "Run", "start_date": "2017-05-31 12:42:08+00:00", "start_date_local": "2017-05-31 20:42:08", "location_country": null, "summary_polyline": "", "average_heartrate": null, "average_speed": 2.051, "elevation_gain": 7.8, "streak": 1}, {"run_id": 15091723529, "name": "\u508d\u665a\u8dd1\u6b65", "distance": 686.9, "moving_time": "0:05:35", "type": "Run", "subtype": "Run", "start_date": "2017-05-31 12:42:08+00:00", "start_date_local": "2017-05-31 20:42:08", "location_country": null, "summary_polyline": "", "average_heartrate": null, "average_speed": 2.051, "elevation_gain": 7.8, "streak": 1}, {"run_id": 15022379100, "name": "\u665a\u95f4\u8dd1\u6b65", "distance": 4646.0, "moving_time": "0:40:48", "type": "Run", "subtype": "Run", "start_date": "2017-06-16 13:03:43+00:00", "start_date_local": "2017-06-16 21:03:43", "location_country": null, "summary_polyline": "", "average_heartrate": null, "average_speed": 1.898, "elevation_gain": 65.1, "streak": 1}, {"run_id": 15041247491, "name": "\u665a\u95f4\u8dd1\u6b65", "distance": 4646.0, "moving_time": "0:40:48", "type": "Run", "subtype": "Run", "start_date": "2017-06-16 13:03:43+00:00", "start_date_local": "2017-06-16 21:03:43", "location_country": null, "summary_polyline": "", "average_heartrate": null, "average_speed": 1.898, "elevation_gain": 65.1, "streak": 1}, {"run_id": 15041454280, "name": "\u665a\u95f4\u8dd1\u6b65", "distance": 4646.0, "moving_time": "0:40:48", "type": "Run", "subtype": "Run", "start_date": "2017-06-16 13:03:43+00:00", "start_date_local": "2017-06-16 21:03:43", "location_country": null, "summary_polyline": "", "average_heartrate": null, "average_speed": 1.898, "elevation_gain": 65.1, "streak": 1}, {"run_id": 15041717032, "name": "\u665a\u95f4\u8dd1\u6b65", "distance": 4646.0, "moving_time": "0:40:48", "type": "Run", "subtype": "Run", "start_date": "2017-06-16 13:03:43+00:00", "start_date_local": "2017-06-16 21:03:43", "location_country": null, "summary_polyline": "", "average_heartrate": null, "average_speed": 1.898, "elevation_gain": 65.1, "streak": 1}, {"run_id": 15045702028, "name": "\u665a\u95f4\u8dd1\u6b65", "distance": 4646.0, "moving_time": "0:40:48", "type": "Run", "subtype": "Run", "start_date": "2017-06-16 13:03:43+00:00", "start_date_local": "2017-06-16 21:03:43", "location_country": null, "summary_polyline": "", "average_heartrate": null, "average_speed": 1.898, "elevation_gain": 65.1, "streak": 1}, {"run_id": 15052053422, "name": "\u665a\u95f4\u8dd1\u6b65", "distance": 4646.0, "moving_time": "0:40:48", "type": "Run", "subtype": "Run", "start_date": "2017-06-16 13:03:43+00:00", "start_date_local": "2017-06-16 21:03:43", "location_country": null, "summary_polyline": "", "average_heartrate": null, "average_speed": 1.898, "elevation_gain": 65.1, "streak": 1}, {"run_id": 15057204052, "name": "\u665a\u95f4\u8dd1\u6b65", "distance": 4646.0, "moving_time": "0:40:48", "type": "Run", "subtype": "Run", "start_date": "2017-06-16 13:03:43+00:00", "start_date_local": "2017-06-16 21:03:43", "location_country": null, "summary_polyline": "", "average_heartrate": null, "average_speed": 1.898, "elevation_gain": 65.1, "streak": 1}, {"run_id": 15063521062, "name": "\u665a\u95f4\u8dd1\u6b65", "distance": 4646.0, "moving_time": "0:40:48", "type": "Run", "subtype": "Run", "start_date": "2017-06-16 13:03:43+00:00", "start_date_local": "2017-06-16 21:03:43", "location_country": null, "summary_polyline": "", "average_heartrate": null, "average_speed": 1.898, "elevation_gain": 64.2, "streak": 1}, {"run_id": 15068585366, "name": "\u665a\u95f4\u8dd1\u6b65", "distance": 4646.0, "moving_time": "0:40:48", "type": "Run", "subtype": "Run", "start_date": "2017-06-16 13:03:43+00:00", "start_date_local": "2017-06-16 21:03:43", "location_country": null, "summary_polyline": "", "average_heartrate": null, "average_speed": 1.898, "elevation_gain": 64.2, "streak": 1}, {"run_id": 15074239438, "name": "\u665a\u95f4\u8dd1\u6b65", "distance": 4646.0, "moving_time": "0:40:48", "type": "Run", "subtype": "Run", "start_date": "2017-06-16 13:03:43+00:00", "start_date_local": "2017-06-16 21:03:43", "location_country": null, "summary_polyline": "", "average_heartrate": null, "average_speed": 1.898, "elevation_gain": 64.2, "streak": 1}, {"run_id": 15084040031, "name": "\u665a\u95f4\u8dd1\u6b65", "distance": 4646.0, "moving_time": "0:40:48", "type": "Run", "subtype": "Run", "start_date": "2017-06-16 13:03:43+00:00", "start_date_local": "2017-06-16 21:03:43", "location_country": null, "summary_polyline": "", "average_heartrate": null, "average_speed": 1.898, "elevation_gain": 64.2, "streak": 1}, {"run_id": 15091723440, "name": "\u665a\u95f4\u8dd1\u6b65", "distance": 4646.0, "moving_time": "0:40:48", "type": "Run", "subtype": "Run", "start_date": "2017-06-16 13:03:43+00:00", "start_date_local": "2017-06-16 21:03:43", "location_country": null, "summary_polyline": "", "average_heartrate": null, "average_speed": 1.898, "elevation_gain": 64.2, "streak": 1}, {"run_id": 15022378688, "name": "\u508d\u665a\u8dd1\u6b65", "distance": 3050.9, "moving_time": "0:22:10", "type": "Run", "subtype": "Run", "start_date": "2017-06-18 12:41:07+00:00", "start_date_local": "2017-06-18 20:41:07", "location_country": null, "summary_polyline": "", "average_heartrate": null, "average_speed": 2.294, "elevation_gain": 51.1, "streak": 1}, {"run_id": 15041247423, "name": "\u508d\u665a\u8dd1\u6b65", "distance": 3050.9, "moving_time": "0:22:10", "type": "Run", "subtype": "Run", "start_date": "2017-06-18 12:41:07+00:00", "start_date_local": "2017-06-18 20:41:07", "location_country": null, "summary_polyline": "", "average_heartrate": null, "average_speed": 2.294, "elevation_gain": 51.1, "streak": 1}, {"run_id": 15041454209, "name": "\u508d\u665a\u8dd1\u6b65", "distance": 3050.9, "moving_time": "0:22:10", "type": "Run", "subtype": "Run", "start_date": "2017-06-18 12:41:07+00:00", "start_date_local": "2017-06-18 20:41:07", "location_country": null, "summary_polyline": "", "average_heartrate": null, "average_speed": 2.294, "elevation_gain": 51.1, "streak": 1}, {"run_id": 15041716582, "name": "\u508d\u665a\u8dd1\u6b65", "distance": 3050.9, "moving_time": "0:22:10", "type": "Run", "subtype": "Run", "start_date": "2017-06-18 12:41:07+00:00", "start_date_local": "2017-06-18 20:41:07", "location_country": null, "summary_polyline": "", "average_heartrate": null, "average_speed": 2.294, "elevation_gain": 51.1, "streak": 1}, {"run_id": 15045701914, "name": "\u508d\u665a\u8dd1\u6b65", "distance": 3050.9, "moving_time": "0:22:10", "type": "Run", "subtype": "Run", "start_date": "2017-06-18 12:41:07+00:00", "start_date_local": "2017-06-18 20:41:07", "location_country": null, "summary_polyline": "", "average_heartrate": null, "average_speed": 2.294, "elevation_gain": 51.1, "streak": 1}, {"run_id": 15052053342, "name": "\u508d\u665a\u8dd1\u6b65", "distance": 3050.9, "moving_time": "0:22:10", "type": "Run", "subtype": "Run", "start_date": "2017-06-18 12:41:07+00:00", "start_date_local": "2017-06-18 20:41:07", "location_country": null, "summary_polyline": "", "average_heartrate": null, "average_speed": 2.294, "elevation_gain": 51.1, "streak": 1}, {"run_id": 15057203947, "name": "\u508d\u665a\u8dd1\u6b65", "distance": 3050.9, "moving_time": "0:22:10", "type": "Run", "subtype": "Run", "start_date": "2017-06-18 12:41:07+00:00", "start_date_local": "2017-06-18 20:41:07", "location_country": null, "summary_polyline": "", "average_heartrate": null, "average_speed": 2.294, "elevation_gain": 51.1, "streak": 1}, {"run_id": 15063520861, "name": "\u508d\u665a\u8dd1\u6b65", "distance": 3050.9, "moving_time": "0:22:10", "type": "Run", "subtype": "Run", "start_date": "2017-06-18 12:41:07+00:00", "start_date_local": "2017-06-18 20:41:07", "location_country": null, "summary_polyline": "", "average_heartrate": null, "average_speed": 2.294, "elevation_gain": 51.0, "streak": 1}, {"run_id": 15068585298, "name": "\u508d\u665a\u8dd1\u6b65", "distance": 3050.9, "moving_time": "0:22:10", "type": "Run", "subtype": "Run", "start_date": "2017-06-18 12:41:07+00:00", "start_date_local": "2017-06-18 20:41:07", "location_country": null, "summary_polyline": "", "average_heartrate": null, "average_speed": 2.294, "elevation_gain": 51.0, "streak": 1}, {"run_id": 15074239339, "name": "\u508d\u665a\u8dd1\u6b65", "distance": 3050.9, "moving_time": "0:22:10", "type": "Run", "subtype": "Run", "start_date": "2017-06-18 12:41:07+00:00", "start_date_local": "2017-06-18 20:41:07", "location_country": null, "summary_polyline": "", "average_heartrate": null, "average_speed": 2.294, "elevation_gain": 51.0, "streak": 1}, {"run_id": 15084039931, "name": "\u508d\u665a\u8dd1\u6b65", "distance": 3050.9, "moving_time": "0:22:10", "type": "Run", "subtype": "Run", "start_date": "2017-06-18 12:41:07+00:00", "start_date_local": "2017-06-18 20:41:07", "location_country": null, "summary_polyline": "", "average_heartrate": null, "average_speed": 2.294, "elevation_gain": 51.0, "streak": 1}, {"run_id": 15091723376, "name": "\u508d\u665a\u8dd1\u6b65", "distance": 3050.9, "moving_time": "0:22:10", "type": "Run", "subtype": "Run", "start_date": "2017-06-18 12:41:07+00:00", "start_date_local": "2017-06-18 20:41:07", "location_country": null, "summary_polyline": "", "average_heartrate": null, "average_speed": 2.294, "elevation_gain": 51.0, "streak": 1}, {"run_id": 15022378271, "name": "\u508d\u665a\u8dd1\u6b65", "distance": 3479.1, "moving_time": "0:26:55", "type": "Run", "subtype": "Run", "start_date": "2017-09-09 12:16:33+00:00", "start_date_local": "2017-09-09 20:16:33", "location_country": null, "summary_polyline": "", "average_heartrate": null, "average_speed": 2.154, "elevation_gain": 59.0, "streak": 1}, {"run_id": 15041247338, "name": "\u508d\u665a\u8dd1\u6b65", "distance": 3479.1, "moving_time": "0:26:55", "type": "Run", "subtype": "Run", "start_date": "2017-09-09 12:16:33+00:00", "start_date_local": "2017-09-09 20:16:33", "location_country": null, "summary_polyline": "", "average_heartrate": null, "average_speed": 2.154, "elevation_gain": 59.0, "streak": 1}, {"run_id": 15041454172, "name": "\u508d\u665a\u8dd1\u6b65", "distance": 3479.1, "moving_time": "0:26:55", "type": "Run", "subtype": "Run", "start_date": "2017-09-09 12:16:33+00:00", "start_date_local": "2017-09-09 20:16:33", "location_country": null, "summary_polyline": "", "average_heartrate": null, "average_speed": 2.154, "elevation_gain": 59.0, "streak": 1}, {"run_id": 15041716519, "name": "\u508d\u665a\u8dd1\u6b65", "distance": 3479.1, "moving_time": "0:26:55", "type": "Run", "subtype": "Run", "start_date": "2017-09-09 12:16:33+00:00", "start_date_local": "2017-09-09 20:16:33", "location_country": null, "summary_polyline": "", "average_heartrate": null, "average_speed": 2.154, "elevation_gain": 59.0, "streak": 1}, {"run_id": 15045701837, "name": "\u508d\u665a\u8dd1\u6b65", "distance": 3479.1, "moving_time": "0:26:55", "type": "Run", "subtype": "Run", "start_date": "2017-09-09 12:16:33+00:00", "start_date_local": "2017-09-09 20:16:33", "location_country": null, "summary_polyline": "", "average_heartrate": null, "average_speed": 2.154, "elevation_gain": 59.0, "streak": 1}, {"run_id": 15052053256, "name": "\u508d\u665a\u8dd1\u6b65", "distance": 3479.1, "moving_time": "0:26:55", "type": "Run", "subtype": "Run", "start_date": "2017-09-09 12:16:33+00:00", "start_date_local": "2017-09-09 20:16:33", "location_country": null, "summary_polyline": "", "average_heartrate": null, "average_speed": 2.154, "elevation_gain": 59.0, "streak": 1}, {"run_id": 15057203743, "name": "\u508d\u665a\u8dd1\u6b65", "distance": 3479.1, "moving_time": "0:26:55", "type": "Run", "subtype": "Run", "start_date": "2017-09-09 12:16:33+00:00", "start_date_local": "2017-09-09 20:16:33", "location_country": null, "summary_polyline": "", "average_heartrate": null, "average_speed": 2.154, "elevation_gain": 59.0, "streak": 1}, {"run_id": 15063520669, "name": "\u508d\u665a\u8dd1\u6b65", "distance": 3479.1, "moving_time": "0:26:55", "type": "Run", "subtype": "Run", "start_date": "2017-09-09 12:16:33+00:00", "start_date_local": "2017-09-09 20:16:33", "location_country": null, "summary_polyline": "", "average_heartrate": null, "average_speed": 2.154, "elevation_gain": 58.6, "streak": 1}, {"run_id": 15068585062, "name": "\u508d\u665a\u8dd1\u6b65", "distance": 3479.1, "moving_time": "0:26:55", "type": "Run", "subtype": "Run", "start_date": "2017-09-09 12:16:33+00:00", "start_date_local": "2017-09-09 20:16:33", "location_country": null, "summary_polyline": "", "average_heartrate": null, "average_speed": 2.154, "elevation_gain": 58.6, "streak": 1}, {"run_id": 15074239250, "name": "\u508d\u665a\u8dd1\u6b65", "distance": 3479.1, "moving_time": "0:26:55", "type": "Run", "subtype": "Run", "start_date": "2017-09-09 12:16:33+00:00", "start_date_local": "2017-09-09 20:16:33", "location_country": null, "summary_polyline": "", "average_heartrate": null, "average_speed": 2.154, "elevation_gain": 58.6, "streak": 1}, {"run_id": 15084039858, "name": "\u508d\u665a\u8dd1\u6b65", "distance": 3479.1, "moving_time": "0:26:55", "type": "Run", "subtype": "Run", "start_date": "2017-09-09 12:16:33+00:00", "start_date_local": "2017-09-09 20:16:33", "location_country": null, "summary_polyline": "", "average_heartrate": null, "average_speed": 2.154, "elevation_gain": 58.6, "streak": 1}, {"run_id": 15091723200, "name": "\u508d\u665a\u8dd1\u6b65", "distance": 3479.1, "moving_time": "0:26:55", "type": "Run", "subtype": "Run", "start_date": "2017-09-09 12:16:33+00:00", "start_date_local": "2017-09-09 20:16:33", "location_country": null, "summary_polyline": "", "average_heartrate": null, "average_speed": 2.154, "elevation_gain": 58.6, "streak": 1}, {"run_id": 15022378063, "name": "\u508d\u665a\u8dd1\u6b65", "distance": 3688.3, "moving_time": "0:26:28", "type": "Run", "subtype": "Run", "start_date": "2017-09-11 12:59:31+00:00", "start_date_local": "2017-09-11 20:59:31", "location_country": null, "summary_polyline": "", "average_heartrate": null, "average_speed": 2.323, "elevation_gain": 59.9, "streak": 1}, {"run_id": 15041247209, "name": "\u508d\u665a\u8dd1\u6b65", "distance": 3688.3, "moving_time": "0:26:28", "type": "Run", "subtype": "Run", "start_date": "2017-09-11 12:59:31+00:00", "start_date_local": "2017-09-11 20:59:31", "location_country": null, "summary_polyline": "", "average_heartrate": null, "average_speed": 2.323, "elevation_gain": 59.9, "streak": 1}, {"run_id": 15041454110, "name": "\u508d\u665a\u8dd1\u6b65", "distance": 3688.3, "moving_time": "0:26:28", "type": "Run", "subtype": "Run", "start_date": "2017-09-11 12:59:31+00:00", "start_date_local": "2017-09-11 20:59:31", "location_country": null, "summary_polyline": "", "average_heartrate": null, "average_speed": 2.323, "elevation_gain": 59.9, "streak": 1}, {"run_id": 15041716329, "name": "\u508d\u665a\u8dd1\u6b65", "distance": 3688.3, "moving_time": "0:26:28", "type": "Run", "subtype": "Run", "start_date": "2017-09-11 12:59:31+00:00", "start_date_local": "2017-09-11 20:59:31", "location_country": null, "summary_polyline": "", "average_heartrate": null, "average_speed": 2.323, "elevation_gain": 59.9, "streak": 1}, {"run_id": 15045701794, "name": "\u508d\u665a\u8dd1\u6b65", "distance": 3688.3, "moving_time": "0:26:28", "type": "Run", "subtype": "Run", "start_date": "2017-09-11 12:59:31+00:00", "start_date_local": "2017-09-11 20:59:31", "location_country": null, "summary_polyline": "", "average_heartrate": null, "average_speed": 2.323, "elevation_gain": 59.9, "streak": 1}, {"run_id": 15052053135, "name": "\u508d\u665a\u8dd1\u6b65", "distance": 3688.3, "moving_time": "0:26:28", "type": "Run", "subtype": "Run", "start_date": "2017-09-11 12:59:31+00:00", "start_date_local": "2017-09-11 20:59:31", "location_country": null, "summary_polyline": "", "average_heartrate": null, "average_speed": 2.323, "elevation_gain": 59.9, "streak": 1}, {"run_id": 15057203684, "name": "\u508d\u665a\u8dd1\u6b65", "distance": 3688.3, "moving_time": "0:26:28", "type": "Run", "subtype": "Run", "start_date": "2017-09-11 12:59:31+00:00", "start_date_local": "2017-09-11 20:59:31", "location_country": null, "summary_polyline": "", "average_heartrate": null, "average_speed": 2.323, "elevation_gain": 59.9, "streak": 1}, {"run_id": 15063520508, "name": "\u508d\u665a\u8dd1\u6b65", "distance": 3688.3, "moving_time": "0:26:28", "type": "Run", "subtype": "Run", "start_date": "2017-09-11 12:59:31+00:00", "start_date_local": "2017-09-11 20:59:31", "location_country": null, "summary_polyline": "", "average_heartrate": null, "average_speed": 2.323, "elevation_gain": 59.0, "streak": 1}, {"run_id": 15068584925, "name": "\u508d\u665a\u8dd1\u6b65", "distance": 3688.3, "moving_time": "0:26:28", "type": "Run", "subtype": "Run", "start_date": "2017-09-11 12:59:31+00:00", "start_date_local": "2017-09-11 20:59:31", "location_country": null, "summary_polyline": "", "average_heartrate": null, "average_speed": 2.323, "elevation_gain": 59.0, "streak": 1}, {"run_id": 15074239191, "name": "\u508d\u665a\u8dd1\u6b65", "distance": 3688.3, "moving_time": "0:26:28", "type": "Run", "subtype": "Run", "start_date": "2017-09-11 12:59:31+00:00", "start_date_local": "2017-09-11 20:59:31", "location_country": null, "summary_polyline": "", "average_heartrate": null, "average_speed": 2.323, "elevation_gain": 59.0, "streak": 1}, {"run_id": 15084039754, "name": "\u508d\u665a\u8dd1\u6b65", "distance": 3688.3, "moving_time": "0:26:28", "type": "Run", "subtype": "Run", "start_date": "2017-09-11 12:59:31+00:00", "start_date_local": "2017-09-11 20:59:31", "location_country": null, "summary_polyline": "", "average_heartrate": null, "average_speed": 2.323, "elevation_gain": 59.0, "streak": 1}, {"run_id": 15091723100, "name": "\u508d\u665a\u8dd1\u6b65", "distance": 3688.3, "moving_time": "0:26:28", "type": "Run", "subtype": "Run", "start_date": "2017-09-11 12:59:31+00:00", "start_date_local": "2017-09-11 20:59:31", "location_country": null, "summary_polyline": "", "average_heartrate": null, "average_speed": 2.323, "elevation_gain": 59.0, "streak": 1}, {"run_id": 15022377271, "name": "\u508d\u665a\u8dd1\u6b65", "distance": 3745.5, "moving_time": "0:26:31", "type": "Run", "subtype": "Run", "start_date": "2017-09-13 12:43:13+00:00", "start_date_local": "2017-09-13 20:43:13", "location_country": null, "summary_polyline": "", "average_heartrate": null, "average_speed": 2.354, "elevation_gain": 61.0, "streak": 1}, {"run_id": 15041247132, "name": "\u508d\u665a\u8dd1\u6b65", "distance": 3745.5, "moving_time": "0:26:31", "type": "Run", "subtype": "Run", "start_date": "2017-09-13 12:43:13+00:00", "start_date_local": "2017-09-13 20:43:13", "location_country": null, "summary_polyline": "", "average_heartrate": null, "average_speed": 2.354, "elevation_gain": 61.0, "streak": 1}, {"run_id": 15041454046, "name": "\u508d\u665a\u8dd1\u6b65", "distance": 3745.5, "moving_time": "0:26:31", "type": "Run", "subtype": "Run", "start_date": "2017-09-13 12:43:13+00:00", "start_date_local": "2017-09-13 20:43:13", "location_country": null, "summary_polyline": "", "average_heartrate": null, "average_speed": 2.354, "elevation_gain": 61.0, "streak": 1}, {"run_id": 15041716076, "name": "\u508d\u665a\u8dd1\u6b65", "distance": 3745.5, "moving_time": "0:26:31", "type": "Run", "subtype": "Run", "start_date": "2017-09-13 12:43:13+00:00", "start_date_local": "2017-09-13 20:43:13", "location_country": null, "summary_polyline": "", "average_heartrate": null, "average_speed": 2.354, "elevation_gain": 61.0, "streak": 1}, {"run_id": 15045701666, "name": "\u508d\u665a\u8dd1\u6b65", "distance": 3745.5, "moving_time": "0:26:31", "type": "Run", "subtype": "Run", "start_date": "2017-09-13 12:43:13+00:00", "start_date_local": "2017-09-13 20:43:13", "location_country": null, "summary_polyline": "", "average_heartrate": null, "average_speed": 2.354, "elevation_gain": 61.0, "streak": 1}, {"run_id": 15052053059, "name": "\u508d\u665a\u8dd1\u6b65", "distance": 3745.5, "moving_time": "0:26:31", "type": "Run", "subtype": "Run", "start_date": "2017-09-13 12:43:13+00:00", "start_date_local": "2017-09-13 20:43:13", "location_country": null, "summary_polyline": "", "average_heartrate": null, "average_speed": 2.354, "elevation_gain": 61.0, "streak": 1}, {"run_id": 15057203643, "name": "\u508d\u665a\u8dd1\u6b65", "distance": 3745.5, "moving_time": "0:26:31", "type": "Run", "subtype": "Run", "start_date": "2017-09-13 12:43:13+00:00", "start_date_local": "2017-09-13 20:43:13", "location_country": null, "summary_polyline": "", "average_heartrate": null, "average_speed": 2.354, "elevation_gain": 61.0, "streak": 1}, {"run_id": 15063520357, "name": "\u508d\u665a\u8dd1\u6b65", "distance": 3745.5, "moving_time": "0:26:31", "type": "Run", "subtype": "Run", "start_date": "2017-09-13 12:43:13+00:00", "start_date_local": "2017-09-13 20:43:13", "location_country": null, "summary_polyline": "", "average_heartrate": null, "average_speed": 2.354, "elevation_gain": 60.2, "streak": 1}, {"run_id": 15068584811, "name": "\u508d\u665a\u8dd1\u6b65", "distance": 3745.5, "moving_time": "0:26:31", "type": "Run", "subtype": "Run", "start_date": "2017-09-13 12:43:13+00:00", "start_date_local": "2017-09-13 20:43:13", "location_country": null, "summary_polyline": "", "average_heartrate": null, "average_speed": 2.354, "elevation_gain": 60.2, "streak": 1}, {"run_id": 15074239098, "name": "\u508d\u665a\u8dd1\u6b65", "distance": 3745.5, "moving_time": "0:26:31", "type": "Run", "subtype": "Run", "start_date": "2017-09-13 12:43:13+00:00", "start_date_local": "2017-09-13 20:43:13", "location_country": null, "summary_polyline": "", "average_heartrate": null, "average_speed": 2.354, "elevation_gain": 60.2, "streak": 1}, {"run_id": 15084039646, "name": "\u508d\u665a\u8dd1\u6b65", "distance": 3745.5, "moving_time": "0:26:31", "type": "Run", "subtype": "Run", "start_date": "2017-09-13 12:43:13+00:00", "start_date_local": "2017-09-13 20:43:13", "location_country": null, "summary_polyline": "", "average_heartrate": null, "average_speed": 2.354, "elevation_gain": 60.2, "streak": 1}, {"run_id": 15091723035, "name": "\u508d\u665a\u8dd1\u6b65", "distance": 3745.5, "moving_time": "0:26:31", "type": "Run", "subtype": "Run", "start_date": "2017-09-13 12:43:13+00:00", "start_date_local": "2017-09-13 20:43:13", "location_country": null, "summary_polyline": "", "average_heartrate": null, "average_speed": 2.354, "elevation_gain": 60.2, "streak": 1}, {"run_id": 15022376919, "name": "\u508d\u665a\u8dd1\u6b65", "distance": 2588.7, "moving_time": "0:18:09", "type": "Run", "subtype": "Run", "start_date": "2017-09-16 12:50:41+00:00", "start_date_local": "2017-09-16 20:50:41", "location_country": null, "summary_polyline": "", "average_heartrate": null, "average_speed": 2.377, "elevation_gain": 45.1, "streak": 1}, {"run_id": 15041247095, "name": "\u508d\u665a\u8dd1\u6b65", "distance": 2588.7, "moving_time": "0:18:09", "type": "Run", "subtype": "Run", "start_date": "2017-09-16 12:50:41+00:00", "start_date_local": "2017-09-16 20:50:41", "location_country": null, "summary_polyline": "", "average_heartrate": null, "average_speed": 2.377, "elevation_gain": 45.1, "streak": 1}, {"run_id": 15041453907, "name": "\u508d\u665a\u8dd1\u6b65", "distance": 2588.7, "moving_time": "0:18:09", "type": "Run", "subtype": "Run", "start_date": "2017-09-16 12:50:41+00:00", "start_date_local": "2017-09-16 20:50:41", "location_country": null, "summary_polyline": "", "average_heartrate": null, "average_speed": 2.377, "elevation_gain": 45.1, "streak": 1}, {"run_id": 15041715832, "name": "\u508d\u665a\u8dd1\u6b65", "distance": 2588.7, "moving_time": "0:18:09", "type": "Run", "subtype": "Run", "start_date": "2017-09-16 12:50:41+00:00", "start_date_local": "2017-09-16 20:50:41", "location_country": null, "summary_polyline": "", "average_heartrate": null, "average_speed": 2.377, "elevation_gain": 45.1, "streak": 1}, {"run_id": 15045701573, "name": "\u508d\u665a\u8dd1\u6b65", "distance": 2588.7, "moving_time": "0:18:09", "type": "Run", "subtype": "Run", "start_date": "2017-09-16 12:50:41+00:00", "start_date_local": "2017-09-16 20:50:41", "location_country": null, "summary_polyline": "", "average_heartrate": null, "average_speed": 2.377, "elevation_gain": 45.1, "streak": 1}, {"run_id": 15052052843, "name": "\u508d\u665a\u8dd1\u6b65", "distance": 2588.7, "moving_time": "0:18:09", "type": "Run", "subtype": "Run", "start_date": "2017-09-16 12:50:41+00:00", "start_date_local": "2017-09-16 20:50:41", "location_country": null, "summary_polyline": "", "average_heartrate": null, "average_speed": 2.377, "elevation_gain": 45.1, "streak": 1}, {"run_id": 15057203343, "name": "\u508d\u665a\u8dd1\u6b65", "distance": 2588.7, "moving_time": "0:18:09", "type": "Run", "subtype": "Run", "start_date": "2017-09-16 12:50:41+00:00", "start_date_local": "2017-09-16 20:50:41", "location_country": null, "summary_polyline": "", "average_heartrate": null, "average_speed": 2.377, "elevation_gain": 45.1, "streak": 1}, {"run_id": 15063520261, "name": "\u508d\u665a\u8dd1\u6b65", "distance": 2588.7, "moving_time": "0:18:09", "type": "Run", "subtype": "Run", "start_date": "2017-09-16 12:50:41+00:00", "start_date_local": "2017-09-16 20:50:41", "location_country": null, "summary_polyline": "", "average_heartrate": null, "average_speed": 2.377, "elevation_gain": 44.2, "streak": 1}, {"run_id": 15068584572, "name": "\u508d\u665a\u8dd1\u6b65", "distance": 2588.7, "moving_time": "0:18:09", "type": "Run", "subtype": "Run", "start_date": "2017-09-16 12:50:41+00:00", "start_date_local": "2017-09-16 20:50:41", "location_country": null, "summary_polyline": "", "average_heartrate": null, "average_speed": 2.377, "elevation_gain": 44.2, "streak": 1}, {"run_id": 15074239043, "name": "\u508d\u665a\u8dd1\u6b65", "distance": 2588.7, "moving_time": "0:18:09", "type": "Run", "subtype": "Run", "start_date": "2017-09-16 12:50:41+00:00", "start_date_local": "2017-09-16 20:50:41", "location_country": null, "summary_polyline": "", "average_heartrate": null, "average_speed": 2.377, "elevation_gain": 44.2, "streak": 1}, {"run_id": 15084039499, "name": "\u508d\u665a\u8dd1\u6b65", "distance": 2588.7, "moving_time": "0:18:09", "type": "Run", "subtype": "Run", "start_date": "2017-09-16 12:50:41+00:00", "start_date_local": "2017-09-16 20:50:41", "location_country": null, "summary_polyline": "", "average_heartrate": null, "average_speed": 2.377, "elevation_gain": 44.2, "streak": 1}, {"run_id": 15091722888, "name": "\u508d\u665a\u8dd1\u6b65", "distance": 2588.7, "moving_time": "0:18:09", "type": "Run", "subtype": "Run", "start_date": "2017-09-16 12:50:41+00:00", "start_date_local": "2017-09-16 20:50:41", "location_country": null, "summary_polyline": "", "average_heartrate": null, "average_speed": 2.377, "elevation_gain": 44.2, "streak": 1}, {"run_id": 15022376230, "name": "\u508d\u665a\u8dd1\u6b65", "distance": 2074.8, "moving_time": "0:15:46", "type": "Run", "subtype": "Run", "start_date": "2017-09-18 12:49:05+00:00", "start_date_local": "2017-09-18 20:49:05", "location_country": null, "summary_polyline": "", "average_heartrate": null, "average_speed": 2.193, "elevation_gain": 35.6, "streak": 1}, {"run_id": 15041247061, "name": "\u508d\u665a\u8dd1\u6b65", "distance": 2074.8, "moving_time": "0:15:46", "type": "Run", "subtype": "Run", "start_date": "2017-09-18 12:49:05+00:00", "start_date_local": "2017-09-18 20:49:05", "location_country": null, "summary_polyline": "", "average_heartrate": null, "average_speed": 2.193, "elevation_gain": 35.6, "streak": 1}, {"run_id": 15041453828, "name": "\u508d\u665a\u8dd1\u6b65", "distance": 2074.8, "moving_time": "0:15:46", "type": "Run", "subtype": "Run", "start_date": "2017-09-18 12:49:05+00:00", "start_date_local": "2017-09-18 20:49:05", "location_country": null, "summary_polyline": "", "average_heartrate": null, "average_speed": 2.193, "elevation_gain": 35.6, "streak": 1}, {"run_id": 15041715769, "name": "\u508d\u665a\u8dd1\u6b65", "distance": 2074.8, "moving_time": "0:15:46", "type": "Run", "subtype": "Run", "start_date": "2017-09-18 12:49:05+00:00", "start_date_local": "2017-09-18 20:49:05", "location_country": null, "summary_polyline": "", "average_heartrate": null, "average_speed": 2.193, "elevation_gain": 35.6, "streak": 1}, {"run_id": 15045701506, "name": "\u508d\u665a\u8dd1\u6b65", "distance": 2074.8, "moving_time": "0:15:46", "type": "Run", "subtype": "Run", "start_date": "2017-09-18 12:49:05+00:00", "start_date_local": "2017-09-18 20:49:05", "location_country": null, "summary_polyline": "", "average_heartrate": null, "average_speed": 2.193, "elevation_gain": 35.6, "streak": 1}, {"run_id": 15052052787, "name": "\u508d\u665a\u8dd1\u6b65", "distance": 2074.8, "moving_time": "0:15:46", "type": "Run", "subtype": "Run", "start_date": "2017-09-18 12:49:05+00:00", "start_date_local": "2017-09-18 20:49:05", "location_country": null, "summary_polyline": "", "average_heartrate": null, "average_speed": 2.193, "elevation_gain": 35.6, "streak": 1}, {"run_id": 15057203189, "name": "\u508d\u665a\u8dd1\u6b65", "distance": 2074.8, "moving_time": "0:15:46", "type": "Run", "subtype": "Run", "start_date": "2017-09-18 12:49:05+00:00", "start_date_local": "2017-09-18 20:49:05", "location_country": null, "summary_polyline": "", "average_heartrate": null, "average_speed": 2.193, "elevation_gain": 35.6, "streak": 1}, {"run_id": 15063519971, "name": "\u508d\u665a\u8dd1\u6b65", "distance": 2074.8, "moving_time": "0:15:46", "type": "Run", "subtype": "Run", "start_date": "2017-09-18 12:49:05+00:00", "start_date_local": "2017-09-18 20:49:05", "location_country": null, "summary_polyline": "", "average_heartrate": null, "average_speed": 2.193, "elevation_gain": 34.9, "streak": 1}, {"run_id": 15068584520, "name": "\u508d\u665a\u8dd1\u6b65", "distance": 2074.8, "moving_time": "0:15:46", "type": "Run", "subtype": "Run", "start_date": "2017-09-18 12:49:05+00:00", "start_date_local": "2017-09-18 20:49:05", "location_country": null, "summary_polyline": "", "average_heartrate": null, "average_speed": 2.193, "elevation_gain": 34.9, "streak": 1}, {"run_id": 15074238974, "name": "\u508d\u665a\u8dd1\u6b65", "distance": 2074.8, "moving_time": "0:15:46", "type": "Run", "subtype": "Run", "start_date": "2017-09-18 12:49:05+00:00", "start_date_local": "2017-09-18 20:49:05", "location_country": null, "summary_polyline": "", "average_heartrate": null, "average_speed": 2.193, "elevation_gain": 34.9, "streak": 1}, {"run_id": 15084039369, "name": "\u508d\u665a\u8dd1\u6b65", "distance": 2074.8, "moving_time": "0:15:46", "type": "Run", "subtype": "Run", "start_date": "2017-09-18 12:49:05+00:00", "start_date_local": "2017-09-18 20:49:05", "location_country": null, "summary_polyline": "", "average_heartrate": null, "average_speed": 2.193, "elevation_gain": 34.9, "streak": 1}, {"run_id": 15091722770, "name": "\u508d\u665a\u8dd1\u6b65", "distance": 2074.8, "moving_time": "0:15:46", "type": "Run", "subtype": "Run", "start_date": "2017-09-18 12:49:05+00:00", "start_date_local": "2017-09-18 20:49:05", "location_country": null, "summary_polyline": "", "average_heartrate": null, "average_speed": 2.193, "elevation_gain": 34.9, "streak": 1}, {"run_id": 15022375891, "name": "\u508d\u665a\u8dd1\u6b65", "distance": 1961.5, "moving_time": "0:15:48", "type": "Run", "subtype": "Run", "start_date": "2021-05-22 12:17:34+00:00", "start_date_local": "2021-05-22 20:17:34", "location_country": null, "summary_polyline": "", "average_heartrate": null, "average_speed": 2.069, "elevation_gain": 5.4, "streak": 1}, {"run_id": 15041246950, "name": "\u508d\u665a\u8dd1\u6b65", "distance": 1961.5, "moving_time": "0:15:48", "type": "Run", "subtype": "Run", "start_date": "2021-05-22 12:17:34+00:00", "start_date_local": "2021-05-22 20:17:34", "location_country": null, "summary_polyline": "", "average_heartrate": null, "average_speed": 2.069, "elevation_gain": 5.4, "streak": 1}, {"run_id": 15041453690, "name": "\u508d\u665a\u8dd1\u6b65", "distance": 1961.5, "moving_time": "0:15:48", "type": "Run", "subtype": "Run", "start_date": "2021-05-22 12:17:34+00:00", "start_date_local": "2021-05-22 20:17:34", "location_country": null, "summary_polyline": "", "average_heartrate": null, "average_speed": 2.069, "elevation_gain": 5.4, "streak": 1}, {"run_id": 15041714838, "name": "\u508d\u665a\u8dd1\u6b65", "distance": 1961.5, "moving_time": "0:15:48", "type": "Run", "subtype": "Run", "start_date": "2021-05-22 12:17:34+00:00", "start_date_local": "2021-05-22 20:17:34", "location_country": null, "summary_polyline": "", "average_heartrate": null, "average_speed": 2.069, "elevation_gain": 5.4, "streak": 1}, {"run_id": 15045701363, "name": "\u508d\u665a\u8dd1\u6b65", "distance": 1961.5, "moving_time": "0:15:48", "type": "Run", "subtype": "Run", "start_date": "2021-05-22 12:17:34+00:00", "start_date_local": "2021-05-22 20:17:34", "location_country": null, "summary_polyline": "", "average_heartrate": null, "average_speed": 2.069, "elevation_gain": 5.4, "streak": 1}, {"run_id": 15052052596, "name": "\u508d\u665a\u8dd1\u6b65", "distance": 1961.5, "moving_time": "0:15:48", "type": "Run", "subtype": "Run", "start_date": "2021-05-22 12:17:34+00:00", "start_date_local": "2021-05-22 20:17:34", "location_country": null, "summary_polyline": "", "average_heartrate": null, "average_speed": 2.069, "elevation_gain": 5.4, "streak": 1}, {"run_id": 15057202803, "name": "\u508d\u665a\u8dd1\u6b65", "distance": 1961.5, "moving_time": "0:15:48", "type": "Run", "subtype": "Run", "start_date": "2021-05-22 12:17:34+00:00", "start_date_local": "2021-05-22 20:17:34", "location_country": null, "summary_polyline": "", "average_heartrate": null, "average_speed": 2.069, "elevation_gain": 5.4, "streak": 1}, {"run_id": 15063519908, "name": "\u508d\u665a\u8dd1\u6b65", "distance": 1961.5, "moving_time": "0:15:48", "type": "Run", "subtype": "Run", "start_date": "2021-05-22 12:17:34+00:00", "start_date_local": "2021-05-22 20:17:34", "location_country": null, "summary_polyline": "", "average_heartrate": null, "average_speed": 2.069, "elevation_gain": 5.4, "streak": 1}, {"run_id": 15068584276, "name": "\u508d\u665a\u8dd1\u6b65", "distance": 1961.5, "moving_time": "0:15:48", "type": "Run", "subtype": "Run", "start_date": "2021-05-22 12:17:34+00:00", "start_date_local": "2021-05-22 20:17:34", "location_country": null, "summary_polyline": "", "average_heartrate": null, "average_speed": 2.069, "elevation_gain": 5.4, "streak": 1}, {"run_id": 15074238824, "name": "\u508d\u665a\u8dd1\u6b65", "distance": 1961.5, "moving_time": "0:15:48", "type": "Run", "subtype": "Run", "start_date": "2021-05-22 12:17:34+00:00", "start_date_local": "2021-05-22 20:17:34", "location_country": null, "summary_polyline": "", "average_heartrate": null, "average_speed": 2.069, "elevation_gain": 5.4, "streak": 1}, {"run_id": 15084039064, "name": "\u508d\u665a\u8dd1\u6b65", "distance": 1961.5, "moving_time": "0:15:48", "type": "Run", "subtype": "Run", "start_date": "2021-05-22 12:17:34+00:00", "start_date_local": "2021-05-22 20:17:34", "location_country": null, "summary_polyline": "", "average_heartrate": null, "average_speed": 2.069, "elevation_gain": 5.4, "streak": 1}, {"run_id": 15091722553, "name": "\u508d\u665a\u8dd1\u6b65", "distance": 1961.5, "moving_time": "0:15:48", "type": "Run", "subtype": "Run", "start_date": "2021-05-22 12:17:34+00:00", "start_date_local": "2021-05-22 20:17:34", "location_country": null, "summary_polyline": "", "average_heartrate": null, "average_speed": 2.069, "elevation_gain": 5.4, "streak": 1}, {"run_id": 15022375409, "name": "\u508d\u665a\u8dd1\u6b65", "distance": 3612.4, "moving_time": "0:33:13", "type": "Run", "subtype": "Run", "start_date": "2022-07-23 11:40:17+00:00", "start_date_local": "2022-07-23 19:40:17", "location_country": "\u9f99\u5c71\u5357\u8def, \u6cbf\u6c5f\u8857\u9053, \u6c5f\u5317\u65b0\u533a, \u6d66\u53e3\u533a, \u5357\u4eac\u5e02, \u6c5f\u82cf\u7701, 210032, \u4e2d\u56fd", "summary_polyline": "mamcEawmsUK`@Dx@JdA@jAElABNERMNMDcAC{@F]DSVE`A@`BTRBR?PCL@x@FH@NH@t@[TMXc@D_@V?@k@OYAa@@KE[JiAFEL?DIBQHKMsIBa@EgAKw@@QE_@O}@EQy@J}@ViDpAw@TKNGCIBW[Qi@g@oBVS", "average_heartrate": null, "average_speed": 1.813, "elevation_gain": 15.5, "streak": 1}, {"run_id": 15041246884, "name": "\u508d\u665a\u8dd1\u6b65", "distance": 3612.4, "moving_time": "0:33:13", "type": "Run", "subtype": "Run", "start_date": "2022-07-23 11:40:17+00:00", "start_date_local": "2022-07-23 19:40:17", "location_country": "\u9f99\u5c71\u5357\u8def, \u6cbf\u6c5f\u8857\u9053, \u6c5f\u5317\u65b0\u533a, \u6d66\u53e3\u533a, \u5357\u4eac\u5e02, \u6c5f\u82cf\u7701, 210032, \u4e2d\u56fd", "summary_polyline": "mamcEawmsUK`@Dx@JdA@jAElABNERMNMDcAC{@F]DSVE`A@`BTRBR?PCL@x@FH@NH@t@[TMXc@D_@V?@k@OYAa@@KE[JiAFEL?DIBQHKMsIBa@EgAKw@@QE_@O}@EQy@J}@ViDpAw@TKNGCIBW[Qi@g@oBVS", "average_heartrate": null, "average_speed": 1.813, "elevation_gain": 15.5, "streak": 1}, {"run_id": 15041453608, "name": "\u508d\u665a\u8dd1\u6b65", "distance": 3612.4, "moving_time": "0:33:13", "type": "Run", "subtype": "Run", "start_date": "2022-07-23 11:40:17+00:00", "start_date_local": "2022-07-23 19:40:17", "location_country": "\u9f99\u5c71\u5357\u8def, \u6cbf\u6c5f\u8857\u9053, \u6c5f\u5317\u65b0\u533a, \u6d66\u53e3\u533a, \u5357\u4eac\u5e02, \u6c5f\u82cf\u7701, 210032, \u4e2d\u56fd", "summary_polyline": "mamcEawmsUK`@Dx@JdA@jAElABNERMNMDcAC{@F]DSVE`A@`BTRBR?PCL@x@FH@NH@t@[TMXc@D_@V?@k@OYAa@@KE[JiAFEL?DIBQHKMsIBa@EgAKw@@QE_@O}@EQy@J}@ViDpAw@TKNGCIBW[Qi@g@oBVS", "average_heartrate": null, "average_speed": 1.813, "elevation_gain": 15.5, "streak": 1}, {"run_id": 15041714528, "name": "\u508d\u665a\u8dd1\u6b65", "distance": 3612.4, "moving_time": "0:33:13", "type": "Run", "subtype": "Run", "start_date": "2022-07-23 11:40:17+00:00", "start_date_local": "2022-07-23 19:40:17", "location_country": "\u9f99\u5c71\u5357\u8def, \u6cbf\u6c5f\u8857\u9053, \u6c5f\u5317\u65b0\u533a, \u6d66\u53e3\u533a, \u5357\u4eac\u5e02, \u6c5f\u82cf\u7701, 210032, \u4e2d\u56fd", "summary_polyline": "mamcEawmsUK`@Dx@JdA@jAElABNERMNMDcAC{@F]DSVE`A@`BTRBR?PCL@x@FH@NH@t@[TMXc@D_@V?@k@OYAa@@KE[JiAFEL?DIBQHKMsIBa@EgAKw@@QE_@O}@EQy@J}@ViDpAw@TKNGCIBW[Qi@g@oBVS", "average_heartrate": null, "average_speed": 1.813, "elevation_gain": 15.5, "streak": 1}, {"run_id": 15045701262, "name": "\u508d\u665a\u8dd1\u6b65", "distance": 3612.4, "moving_time": "0:33:13", "type": "Run", "subtype": "Run", "start_date": "2022-07-23 11:40:17+00:00", "start_date_local": "2022-07-23 19:40:17", "location_country": "\u9f99\u5c71\u5357\u8def, \u6cbf\u6c5f\u8857\u9053, \u6c5f\u5317\u65b0\u533a, \u6d66\u53e3\u533a, \u5357\u4eac\u5e02, \u6c5f\u82cf\u7701, 210032, \u4e2d\u56fd", "summary_polyline": "mamcEawmsUK`@Dx@JdA@jAElABNERMNMDcAC{@F]DSVE`A@`BTRBR?PCL@x@FH@NH@t@[TMXc@D_@V?@k@OYAa@@KE[JiAFEL?DIBQHKMsIBa@EgAKw@@QE_@O}@EQy@J}@ViDpAw@TKNGCIBW[Qi@g@oBVS", "average_heartrate": null, "average_speed": 1.813, "elevation_gain": 15.5, "streak": 1}, {"run_id": 15052052486, "name": "\u508d\u665a\u8dd1\u6b65", "distance": 3612.4, "moving_time": "0:33:13", "type": "Run", "subtype": "Run", "start_date": "2022-07-23 11:40:17+00:00", "start_date_local": "2022-07-23 19:40:17", "location_country": "\u9f99\u5c71\u5357\u8def, \u6cbf\u6c5f\u8857\u9053, \u6c5f\u5317\u65b0\u533a, \u6d66\u53e3\u533a, \u5357\u4eac\u5e02, \u6c5f\u82cf\u7701, 210032, \u4e2d\u56fd", "summary_polyline": "mamcEawmsUK`@Dx@JdA@jAElABNERMNMDcAC{@F]DSVE`A@`BTRBR?PCL@x@FH@NH@t@[TMXc@D_@V?@k@OYAa@@KE[JiAFEL?DIBQHKMsIBa@EgAKw@@QE_@O}@EQy@J}@ViDpAw@TKNGCIBW[Qi@g@oBVS", "average_heartrate": null, "average_speed": 1.813, "elevation_gain": 15.5, "streak": 1}, {"run_id": 15057202632, "name": "\u508d\u665a\u8dd1\u6b65", "distance": 3612.4, "moving_time": "0:33:13", "type": "Run", "subtype": "Run", "start_date": "2022-07-23 11:40:17+00:00", "start_date_local": "2022-07-23 19:40:17", "location_country": "\u9f99\u5c71\u5357\u8def, \u6cbf\u6c5f\u8857\u9053, \u6c5f\u5317\u65b0\u533a, \u6d66\u53e3\u533a, \u5357\u4eac\u5e02, \u6c5f\u82cf\u7701, 210032, \u4e2d\u56fd", "summary_polyline": "mamcEawmsUK`@Dx@JdA@jAElABNERMNMDcAC{@F]DSVE`A@`BTRBR?PCL@x@FH@NH@t@[TMXc@D_@V?@k@OYAa@@KE[JiAFEL?DIBQHKMsIBa@EgAKw@@QE_@O}@EQy@J}@ViDpAw@TKNGCIBW[Qi@g@oBVS", "average_heartrate": null, "average_speed": 1.813, "elevation_gain": 15.5, "streak": 1}, {"run_id": 15063519876, "name": "\u508d\u665a\u8dd1\u6b65", "distance": 3612.4, "moving_time": "0:33:19", "type": "Run", "subtype": "Run", "start_date": "2022-07-23 11:40:17+00:00", "start_date_local": "2022-07-23 19:40:17", "location_country": "\u9f99\u5c71\u5357\u8def, \u6cbf\u6c5f\u8857\u9053, \u6c5f\u5317\u65b0\u533a, \u6d66\u53e3\u533a, \u5357\u4eac\u5e02, \u6c5f\u82cf\u7701, 210032, \u4e2d\u56fd", "summary_polyline": "mamcEawmsUK`@Dx@JdA@jAElABNERMNMDcAC{@F]DSVE`A@`BTRBR?PCL@x@FH@NH@t@[TMXc@D_@V?@k@OYAa@@KE[JiAFEL?DIBQHKMsIBa@EgAKw@@QE_@O}@EQy@J}@ViDpAw@TKNGCIBW[Qi@g@oBVS", "average_heartrate": null, "average_speed": 1.807, "elevation_gain": 15.2, "streak": 1}, {"run_id": 15068584109, "name": "\u508d\u665a\u8dd1\u6b65", "distance": 3612.4, "moving_time": "0:33:19", "type": "Run", "subtype": "Run", "start_date": "2022-07-23 11:40:17+00:00", "start_date_local": "2022-07-23 19:40:17", "location_country": "\u9f99\u5c71\u5357\u8def, \u6cbf\u6c5f\u8857\u9053, \u6c5f\u5317\u65b0\u533a, \u6d66\u53e3\u533a, \u5357\u4eac\u5e02, \u6c5f\u82cf\u7701, 210032, \u4e2d\u56fd", "summary_polyline": "mamcEawmsUK`@Dx@JdA@jAElABNERMNMDcAC{@F]DSVE`A@`BTRBR?PCL@x@FH@NH@t@[TMXc@D_@V?@k@OYAa@@KE[JiAFEL?DIBQHKMsIBa@EgAKw@@QE_@O}@EQy@J}@ViDpAw@TKNGCIBW[Qi@g@oBVS", "average_heartrate": null, "average_speed": 1.807, "elevation_gain": 15.2, "streak": 1}, {"run_id": 15074238693, "name": "\u508d\u665a\u8dd1\u6b65", "distance": 3612.4, "moving_time": "0:33:19", "type": "Run", "subtype": "Run", "start_date": "2022-07-23 11:40:17+00:00", "start_date_local": "2022-07-23 19:40:17", "location_country": "\u9f99\u5c71\u5357\u8def, \u6cbf\u6c5f\u8857\u9053, \u6c5f\u5317\u65b0\u533a, \u6d66\u53e3\u533a, \u5357\u4eac\u5e02, \u6c5f\u82cf\u7701, 210032, \u4e2d\u56fd", "summary_polyline": "mamcEawmsUK`@Dx@JdA@jAElABNERMNMDcAC{@F]DSVE`A@`BTRBR?PCL@x@FH@NH@t@[TMXc@D_@V?@k@OYAa@@KE[JiAFEL?DIBQHKMsIBa@EgAKw@@QE_@O}@EQy@J}@ViDpAw@TKNGCIBW[Qi@g@oBVS", "average_heartrate": null, "average_speed": 1.807, "elevation_gain": 15.2, "streak": 1}, {"run_id": 15084038934, "name": "\u508d\u665a\u8dd1\u6b65", "distance": 3612.4, "moving_time": "0:33:19", "type": "Run", "subtype": "Run", "start_date": "2022-07-23 11:40:17+00:00", "start_date_local": "2022-07-23 19:40:17", "location_country": "\u9f99\u5c71\u5357\u8def, \u6cbf\u6c5f\u8857\u9053, \u6c5f\u5317\u65b0\u533a, \u6d66\u53e3\u533a, \u5357\u4eac\u5e02, \u6c5f\u82cf\u7701, 210032, \u4e2d\u56fd", "summary_polyline": "mamcEawmsUK`@Dx@JdA@jAElABNERMNMDcAC{@F]DSVE`A@`BTRBR?PCL@x@FH@NH@t@[TMXc@D_@V?@k@OYAa@@KE[JiAFEL?DIBQHKMsIBa@EgAKw@@QE_@O}@EQy@J}@ViDpAw@TKNGCIBW[Qi@g@oBVS", "average_heartrate": null, "average_speed": 1.807, "elevation_gain": 15.2, "streak": 1}, {"run_id": 15091722240, "name": "\u508d\u665a\u8dd1\u6b65", "distance": 3612.4, "moving_time": "0:33:19", "type": "Run", "subtype": "Run", "start_date": "2022-07-23 11:40:17+00:00", "start_date_local": "2022-07-23 19:40:17", "location_country": "\u9f99\u5c71\u5357\u8def, \u6cbf\u6c5f\u8857\u9053, \u6c5f\u5317\u65b0\u533a, \u6d66\u53e3\u533a, \u5357\u4eac\u5e02, \u6c5f\u82cf\u7701, 210032, \u4e2d\u56fd", "summary_polyline": "mamcEawmsUK`@Dx@JdA@jAElABNERMNMDcAC{@F]DSVE`A@`BTRBR?PCL@x@FH@NH@t@[TMXc@D_@V?@k@OYAa@@KE[JiAFEL?DIBQHKMsIBa@EgAKw@@QE_@O}@EQy@J}@ViDpAw@TKNGCIBW[Qi@g@oBVS", "average_heartrate": null, "average_speed": 1.807, "elevation_gain": 15.2, "streak": 1}, {"run_id": 8630528676, "name": "\u508d\u665a\u8dd1\u6b65", "distance": 2157.3, "moving_time": "0:14:39", "type": "Run", "subtype": "Run", "start_date": "2023-02-27 12:44:19+00:00", "start_date_local": "2023-02-27 20:44:19", "location_country": null, "summary_polyline": "", "average_heartrate": 145.4, "average_speed": 2.454, "elevation_gain": 40.8, "streak": 1}, {"run_id": 8674932899, "name": "\u508d\u665a\u8dd1\u6b65", "distance": 958.9, "moving_time": "0:05:12", "type": "Run", "subtype": "Run", "start_date": "2023-03-07 12:49:50+00:00", "start_date_local": "2023-03-07 20:49:50", "location_country": null, "summary_polyline": "", "average_heartrate": 134.4, "average_speed": 3.073, "elevation_gain": 19.3, "streak": 1}, {"run_id": 15022374856, "name": "\u508d\u665a\u8dd1\u6b65", "distance": 2408.8, "moving_time": "0:20:21", "type": "Run", "subtype": "Run", "start_date": "2024-03-23 12:04:05+00:00", "start_date_local": "2024-03-23 20:04:05", "location_country": null, "summary_polyline": "", "average_heartrate": null, "average_speed": 1.973, "elevation_gain": 13.0, "streak": 1}, {"run_id": 15041246838, "name": "\u508d\u665a\u8dd1\u6b65", "distance": 2408.8, "moving_time": "0:20:21", "type": "Run", "subtype": "Run", "start_date": "2024-03-23 12:04:05+00:00", "start_date_local": "2024-03-23 20:04:05", "location_country": null, "summary_polyline": "", "average_heartrate": null, "average_speed": 1.973, "elevation_gain": 13.0, "streak": 1}, {"run_id": 15041453397, "name": "\u508d\u665a\u8dd1\u6b65", "distance": 2408.8, "moving_time": "0:20:21", "type": "Run", "subtype": "Run", "start_date": "2024-03-23 12:04:05+00:00", "start_date_local": "2024-03-23 20:04:05", "location_country": null, "summary_polyline": "", "average_heartrate": null, "average_speed": 1.973, "elevation_gain": 13.0, "streak": 1}, {"run_id": 15041713554, "name": "\u508d\u665a\u8dd1\u6b65", "distance": 2408.8, "moving_time": "0:20:21", "type": "Run", "subtype": "Run", "start_date": "2024-03-23 12:04:05+00:00", "start_date_local": "2024-03-23 20:04:05", "location_country": null, "summary_polyline": "", "average_heartrate": null, "average_speed": 1.973, "elevation_gain": 13.0, "streak": 1}, {"run_id": 15045701087, "name": "\u508d\u665a\u8dd1\u6b65", "distance": 2408.8, "moving_time": "0:20:21", "type": "Run", "subtype": "Run", "start_date": "2024-03-23 12:04:05+00:00", "start_date_local": "2024-03-23 20:04:05", "location_country": null, "summary_polyline": "", "average_heartrate": null, "average_speed": 1.973, "elevation_gain": 13.0, "streak": 1}, {"run_id": 15052052106, "name": "\u508d\u665a\u8dd1\u6b65", "distance": 2408.8, "moving_time": "0:20:21", "type": "Run", "subtype": "Run", "start_date": "2024-03-23 12:04:05+00:00", "start_date_local": "2024-03-23 20:04:05", "location_country": null, "summary_polyline": "", "average_heartrate": null, "average_speed": 1.973, "elevation_gain": 13.0, "streak": 1}, {"run_id": 15057202324, "name": "\u508d\u665a\u8dd1\u6b65", "distance": 2408.8, "moving_time": "0:20:21", "type": "Run", "subtype": "Run", "start_date": "2024-03-23 12:04:05+00:00", "start_date_local": "2024-03-23 20:04:05", "location_country": null, "summary_polyline": "", "average_heartrate": null, "average_speed": 1.973, "elevation_gain": 13.0, "streak": 1}, {"run_id": 15063519741, "name": "\u508d\u665a\u8dd1\u6b65", "distance": 2408.8, "moving_time": "0:20:21", "type": "Run", "subtype": "Run", "start_date": "2024-03-23 12:04:05+00:00", "start_date_local": "2024-03-23 20:04:05", "location_country": null, "summary_polyline": "", "average_heartrate": null, "average_speed": 1.973, "elevation_gain": 11.0, "streak": 1}, {"run_id": 15068583867, "name": "\u508d\u665a\u8dd1\u6b65", "distance": 2408.8, "moving_time": "0:20:21", "type": "Run", "subtype": "Run", "start_date": "2024-03-23 12:04:05+00:00", "start_date_local": "2024-03-23 20:04:05", "location_country": null, "summary_polyline": "", "average_heartrate": null, "average_speed": 1.973, "elevation_gain": 11.0, "streak": 1}, {"run_id": 15074238647, "name": "\u508d\u665a\u8dd1\u6b65", "distance": 2408.8, "moving_time": "0:20:21", "type": "Run", "subtype": "Run", "start_date": "2024-03-23 12:04:05+00:00", "start_date_local": "2024-03-23 20:04:05", "location_country": null, "summary_polyline": "", "average_heartrate": null, "average_speed": 1.973, "elevation_gain": 11.0, "streak": 1}, {"run_id": 15084038810, "name": "\u508d\u665a\u8dd1\u6b65", "distance": 2408.8, "moving_time": "0:20:21", "type": "Run", "subtype": "Run", "start_date": "2024-03-23 12:04:05+00:00", "start_date_local": "2024-03-23 20:04:05", "location_country": null, "summary_polyline": "", "average_heartrate": null, "average_speed": 1.973, "elevation_gain": 11.0, "streak": 1}, {"run_id": 15091722053, "name": "\u508d\u665a\u8dd1\u6b65", "distance": 2408.8, "moving_time": "0:20:21", "type": "Run", "subtype": "Run", "start_date": "2024-03-23 12:04:05+00:00", "start_date_local": "2024-03-23 20:04:05", "location_country": null, "summary_polyline": "", "average_heartrate": null, "average_speed": 1.973, "elevation_gain": 11.0, "streak": 1}, {"run_id": 11020637276, "name": "\u508d\u665a\u8dd1\u6b65", "distance": 2206.0, "moving_time": "0:10:23", "type": "Run", "subtype": "Run", "start_date": "2024-03-23 12:05:31+00:00", "start_date_local": "2024-03-23 20:05:31", "location_country": null, "summary_polyline": "", "average_heartrate": 128.2, "average_speed": 3.541, "elevation_gain": 12.5, "streak": 1}, {"run_id": 15022374174, "name": "\u508d\u665a\u8dd1\u6b65", "distance": 4811.5, "moving_time": "0:47:46", "type": "Run", "subtype": "Run", "start_date": "2025-07-01 12:22:36+00:00", "start_date_local": "2025-07-01 20:22:36", "location_country": null, "summary_polyline": "", "average_heartrate": 131.5, "average_speed": 1.679, "elevation_gain": 83.8, "streak": 1}, {"run_id": 15022367453, "name": "\u508d\u665a\u8dd1\u6b65", "distance": 5082.4, "moving_time": "0:50:28", "type": "Run", "subtype": "Run", "start_date": "2025-07-02 12:18:55+00:00", "start_date_local": "2025-07-02 20:18:55", "location_country": null, "summary_polyline": "", "average_heartrate": 128.7, "average_speed": 1.678, "elevation_gain": 88.3, "streak": 2}, {"run_id": 15022361795, "name": "\u508d\u665a\u8dd1\u6b65", "distance": 4343.7, "moving_time": "0:42:37", "type": "Run", "subtype": "Run", "start_date": "2025-07-03 12:21:25+00:00", "start_date_local": "2025-07-03 20:21:25", "location_country": null, "summary_polyline": "", "average_heartrate": 127.1, "average_speed": 1.699, "elevation_gain": 76.4, "streak": 3}, {"run_id": 15022359075, "name": "\u665a\u95f4\u8dd1\u6b65", "distance": 4386.2, "moving_time": "0:40:16", "type": "Run", "subtype": "Run", "start_date": "2025-07-04 13:04:54+00:00", "start_date_local": "2025-07-04 21:04:54", "location_country": null, "summary_polyline": "", "average_heartrate": 139.5, "average_speed": 1.815, "elevation_gain": 77.8, "streak": 4}, {"run_id": 15022356308, "name": "\u508d\u665a\u8dd1\u6b65", "distance": 5432.4, "moving_time": "0:53:58", "type": "Run", "subtype": "Run", "start_date": "2025-07-05 12:45:05+00:00", "start_date_local": "2025-07-05 20:45:05", "location_country": null, "summary_polyline": "", "average_heartrate": 134.3, "average_speed": 1.678, "elevation_gain": 92.5, "streak": 5}, {"run_id": 15030767609, "name": "\u508d\u665a\u8dd1\u6b65", "distance": 5453.1, "moving_time": "0:52:54", "type": "Run", "subtype": "Run", "start_date": "2025-07-06 12:39:54+00:00", "start_date_local": "2025-07-06 20:39:54", "location_country": null, "summary_polyline": "", "average_heartrate": 139.4, "average_speed": 1.718, "elevation_gain": 100.8, "streak": 6}, {"run_id": 15041083662, "name": "\u508d\u665a\u8dd1\u6b65", "distance": 5337.5, "moving_time": "0:50:32", "type": "Run", "subtype": "Run", "start_date": "2025-07-07 12:16:16+00:00", "start_date_local": "2025-07-07 20:16:16", "location_country": null, "summary_polyline": "", "average_heartrate": 132.8, "average_speed": 1.76, "elevation_gain": 97.0, "streak": 7}, {"run_id": 15045699106, "name": "\u508d\u665a\u8dd1\u6b65", "distance": 5720.1, "moving_time": "0:50:46", "type": "Run", "subtype": "Run", "start_date": "2025-07-08 12:14:48+00:00", "start_date_local": "2025-07-08 20:14:48", "location_country": null, "summary_polyline": "", "average_heartrate": 145.1, "average_speed": 1.878, "elevation_gain": 95.7, "streak": 8}, {"run_id": 15057200218, "name": "\u508d\u665a\u8dd1\u6b65", "distance": 5891.1, "moving_time": "0:55:00", "type": "Run", "subtype": "Run", "start_date": "2025-07-09 12:19:48+00:00", "start_date_local": "2025-07-09 20:19:48", "location_country": null, "summary_polyline": "", "average_heartrate": 131.0, "average_speed": 1.785, "elevation_gain": 104.5, "streak": 9}, {"run_id": 15068581533, "name": "\u508d\u665a\u8dd1\u6b65", "distance": 5120.5, "moving_time": "0:50:30", "type": "Run", "subtype": "Run", "start_date": "2025-07-10 12:47:37+00:00", "start_date_local": "2025-07-10 20:47:37", "location_country": null, "summary_polyline": "", "average_heartrate": 118.3, "average_speed": 1.69, "elevation_gain": 93.3, "streak": 10}, {"run_id": 15091719638, "name": "\u508d\u665a\u8dd1\u6b65", "distance": 1712.4, "moving_time": "0:14:56", "type": "Run", "subtype": "Run", "start_date": "2025-07-12 12:38:22+00:00", "start_date_local": "2025-07-12 20:38:22", "location_country": null, "summary_polyline": "", "average_heartrate": 127.8, "average_speed": 1.911, "elevation_gain": 30.3, "streak": 1}, {"run_id": 15091719545, "name": "\u508d\u665a\u8dd1\u6b65", "distance": 5093.3, "moving_time": "0:47:13", "type": "Run", "subtype": "Run", "start_date": "2025-07-12 12:53:51+00:00", "start_date_local": "2025-07-12 20:53:51", "location_country": null, "summary_polyline": "", "average_heartrate": 134.6, "average_speed": 1.798, "elevation_gain": 90.0, "streak": 1}, {"run_id": 15091554176, "name": "\u665a\u95f4\u8dd1\u6b65", "distance": 6864.2, "moving_time": "1:02:56", "type": "Run", "subtype": "Run", "start_date": "2025-07-12 16:39:02+00:00", "start_date_local": "2025-07-13 00:39:02", "location_country": null, "summary_polyline": "", "average_heartrate": null, "average_speed": 1.818, "elevation_gain": 124.9, "streak": 2}]